ofxstatement_french-1.5.0-py3.10-nspkg.pth
ofxstatement/plugins/fr/__init__.py
ofxstatement/plugins/fr/banquepopulaire.py
ofxstatement/plugins/fr/statement.py
ofxstatement_french-1.5.0.dist-info/METADATA
ofxstatement_french-1.5.0.dist-info/WHEEL
ofxstatement_french-1.5.0.dist-info/entry_points.txt
ofxstatement_french-1.5.0.dist-info/namespace_packages.txt
ofxstatement_french-1.5.0.dist-info/top_level.txt
ofxstatement_french-1.5.0.dist-info/zip-safe
ofxstatement_french-1.5.0.dist-info/RECORD
