Metadata-Version: 2.1
Name: ofxstatement-french
Version: 1.5.0
Summary: OFXStatement plugin for french financial institutions like BanquePopulaire.
Home-page: https://github.com/gpaulissen/ofxstatement-french
Author: Gert-Jan Paulissen
Author-email: gert.jan.paulissen@gmail.com
License: GPLv3
Keywords: ofx,banking,statement,BanquePopulaire
Classifier: Development Status :: 6 - Mature
Classifier: Programming Language :: Python :: 3
Classifier: Natural Language :: English
Classifier: Topic :: Office/Business :: Financial :: Accounting
Classifier: Topic :: Utilities
Classifier: Environment :: Console
Classifier: Operating System :: OS Independent
Classifier: License :: OSI Approved :: GNU General Public License v3 (GPLv3)
Requires-Dist: ofxstatement >0.6.4
Requires-Dist: pdftotext
Requires-Dist: beautifulsoup4
Provides-Extra: test
Requires-Dist: pyyaml ; extra == 'test'
Requires-Dist: pytest ; extra == 'test'
Requires-Dist: pytest-cache ; extra == 'test'
Requires-Dist: pytest-cover ; extra == 'test'
Requires-Dist: pytest-flakes ; extra == 'test'
Requires-Dist: pytest-pycodestyle ; extra == 'test'
Requires-Dist: flake8 ; extra == 'test'
